plcd/__init__.py
plcd/__main__.py
plcd/ping.py
plcd/plc-ports.dat
plcd-0.1.6.dist-info/METADATA
plcd-0.1.6.dist-info/WHEEL
plcd-0.1.6.dist-info/licenses/LICENSE
plcd-0.1.6.dist-info/RECORD
