Metadata-Version: 2.1
Name: plcd
Version: 0.1.6
Summary: A lightweight PLC uptime monitor
Author: LibreCS
License:                     GNU GENERAL PUBLIC LICENSE
Requires-Python: >=3.7
